bootstrap.py
buildout.cfg
changes.txt
setup.py
todo.txt
src/ore/__init__.py
src/ore.xapian.egg-info/PKG-INFO
src/ore.xapian.egg-info/SOURCES.txt
src/ore.xapian.egg-info/dependency_links.txt
src/ore.xapian.egg-info/namespace_packages.txt
src/ore.xapian.egg-info/not-zip-safe
src/ore.xapian.egg-info/requires.txt
src/ore.xapian.egg-info/top_level.txt
src/ore/xapian/__init__.py
src/ore/xapian/configure.zcml
src/ore/xapian/index.py
src/ore/xapian/interfaces.py
src/ore/xapian/meta.zcml
src/ore/xapian/operation.py
src/ore/xapian/queue.py
src/ore/xapian/readme.txt
src/ore/xapian/resolver.py
src/ore/xapian/search.py
src/ore/xapian/subscriber.py
src/ore/xapian/tests.py
src/ore/xapian/zcml.py