Metadata-Version: 1.0
Name: ore.xapian
Version: 0.5.0
Summary: A Xapian Content Indexing/Searching Framework for Zope3
Home-page: https://svn.objectrealms.net/svn/public/ore.xapian/
Author: Kapil Thangavelu
Author-email: kapil.foss@gmail.com
License: GPL
Keywords: zope3 index search xapian xappy
Platform: UNKNOWN
Classifier: Intended Audience :: Developers
Classifier: Framework :: Zope3
